setup.cfg
setup.py
src/bd2k/__init__.py
src/bd2k/util/__init__.py
src/bd2k/util/collections.py
src/bd2k/util/d32.py
src/bd2k/util/d64.py
src/bd2k/util/exceptions.py
src/bd2k/util/expando.py
src/bd2k/util/files.py
src/bd2k/util/fnmatch.py
src/bd2k/util/hashes.py
src/bd2k/util/humanize.py
src/bd2k/util/iterables.py
src/bd2k/util/lockfile.py
src/bd2k/util/logging.py
src/bd2k/util/objects.py
src/bd2k/util/processes.py
src/bd2k/util/retry.py
src/bd2k/util/shell.py
src/bd2k/util/strings.py
src/bd2k/util/threading.py
src/bd2k/util/throttle.py
src/bd2k/util/ec2/__init__.py
src/bd2k/util/ec2/credentials.py
src/bd2k/util/ec2/test/__init__.py
src/bd2k/util/ec2/test/test_credentials.py
src/bd2k/util/test/__init__.py
src/bd2k/util/test/test_d32.py
src/bd2k/util/test/test_d64.py
src/bd2k/util/test/test_files.py
src/bd2k/util/test/test_panic.py
src/bd2k/util/test/test_strings.py
src/bd2k/util/xml/__init__.py
src/bd2k/util/xml/builder.py
src/bd2k_python_lib.egg-info/PKG-INFO
src/bd2k_python_lib.egg-info/SOURCES.txt
src/bd2k_python_lib.egg-info/dependency_links.txt
src/bd2k_python_lib.egg-info/namespace_packages.txt
src/bd2k_python_lib.egg-info/pbr.json
src/bd2k_python_lib.egg-info/requires.txt
src/bd2k_python_lib.egg-info/top_level.txt