Metadata-Version: 1.0
Name: bd2k-python-lib
Version: 1.14a1.dev48
Summary: The BD2K Python module kitchen sink
Home-page: https://github.com/BD2KGenomics/bd2k-python-lib
Author: Hannes Schmidt
Author-email: hannes@ucsc.edu
License: UNKNOWN
Platform: UNKNOWN
